ActionSelection/ActionSelection.py
ActionSelection/ActionSelectionImpl.py
ActionSelection/__init__.py
AttentionCodelets/AttentionCodelet.py
AttentionCodelets/AttentionCodeletImpl.py
AttentionCodelets/__init__.py
Configurations/Config.py
Configurations/Sensors.py
Configurations/__init__.py
Environment/AtariEnvironment.py
Environment/Environment.py
Environment/FrozenLakeEnvironment.py
Environment/GodotEnvironment.py
Environment/__init__.py
Framework/__init__.py
Framework/Agents/Agent.py
Framework/Agents/Alarms_Control_Agent.py
Framework/Agents/Minimal_Conscious_Agent.py
Framework/Agents/Minimal_Reactive_Agent.py
Framework/Agents/__init__.py
Framework/Initialization/AgentFactory.py
Framework/Initialization/ConcreteAgentFactory.py
Framework/Initialization/__init__.py
Framework/Shared/Activatible.py
Framework/Shared/ActivatibleImpl.py
Framework/Shared/ExtendedID.py
Framework/Shared/Learnable.py
Framework/Shared/LearnableImpl.py
Framework/Shared/Link.py
Framework/Shared/LinkImpl.py
Framework/Shared/Node.py
Framework/Shared/NodeImpl.py
Framework/Shared/NodeStructure.py
Framework/Shared/NodeStructureImpl.py
Framework/Shared/__init__.py
Framework/Strategies/DecayStrategy.py
Framework/Strategies/ExciteStrategy.py
Framework/Strategies/LinearDecayStrategy.py
Framework/Strategies/LinearExciteStrategy.py
Framework/Strategies/TotalActivationStrategy.py
Framework/Strategies/WeightedTotalActivationStrategy.py
Framework/Strategies/__init__.py
Framework/Tasks/Codelet.py
Framework/Tasks/CodeletImpl.py
Framework/Tasks/TaskManager.py
Framework/Tasks/__init__.py
GlobalWorkspace/Coalition.py
GlobalWorkspace/CoalitionImpl.py
GlobalWorkspace/GlobalWorkSpace.py
GlobalWorkspace/GlobalWorkSpaceImpl.py
GlobalWorkspace/__init__.py
Module/ModuleObserver.py
Module/ModuleSubject.py
Module/__init__.py
Module/Initialization/DefaultLogger.py
Module/Initialization/ModuleInterface.py
Module/Initialization/__init__.py
MotorPlanExecution/MotorPlanExecution.py
MotorPlanExecution/MotorPlanExecutionImpl.py
lidapy-0.3.3.dist-info/licenses/LICENSE
lidapy-0.3.3.dist-info/METADATA
lidapy-0.3.3.dist-info/WHEEL
lidapy-0.3.3.dist-info/entry_points.txt
lidapy-0.3.3.dist-info/top_level.txt
lidapy-0.3.3.dist-info/RECORD
